Metadata-Version: 2.1
Name: pyconductor
Version: 0.1.3
Summary: Conductor python client
Home-page: https://github.com/skylarkdrones/pyconductor
Author: Samarth Hattangady
Author-email: samhattangady@gmail.com
License: Apache 2.0
Keywords: netflix,conductor,pyconductor
Platform: UNKNOWN
